pyrng/__init__.py
pyrng/main.py
pyrng-0.1.2.dist-info/licenses/LICENSE
pyrng-0.1.2.dist-info/METADATA
pyrng-0.1.2.dist-info/WHEEL
pyrng-0.1.2.dist-info/top_level.txt
pyrng-0.1.2.dist-info/RECORD
