Metadata-Version: 2.4
Name: pyrng
Version: 0.1.2
Summary: Chained algorithm ephemeral password and PIN generator.
Author-email: Simonko-912 <imnyancat@protonmail.com>
License: MIT
Classifier: Programming Language :: Python :: 3
Classifier: License :: OSI Approved :: MIT License
Classifier: Operating System :: OS Independent
Requires-Python: >=3.10
License-File: LICENSE
Dynamic: license-file
